.readthedocs.yaml
CONTRIBUTING.md
LICENSE
MANIFEST.in
Makefile
README.md
pyproject.toml
setup.py
Augmentum/Augmentum.py
Augmentum.egg-info/PKG-INFO
Augmentum.egg-info/SOURCES.txt
Augmentum.egg-info/dependency_links.txt
Augmentum.egg-info/requires.txt
Augmentum.egg-info/top_level.txt
Augmentum/data/.gitkeep
Augmentum/tests/__init__.py
Augmentum/tests/test_all.py
docs/Makefile
docs/make.bat
docs/source/Augmentum.rst
docs/source/conf.py
docs/source/examples.md
docs/source/index.rst
docs/source/installation.md
docs/source/modules.rst