Metadata-Version: 2.1
Name: Augmentum
Version: 0.1.2
Summary: A library for doing image augmentation
Author-email: Kerim Kurttepeli <kk3084@columbia.edu>
License:                                  Apache License
Project-URL: repository, https://github.com/kurttepelikerim/Augmentum
Classifier: Programming Language :: Python :: 3.10
Requires-Python: >=3.7
Provides-Extra: develop
License-File: LICENSE
